nowplaypadgen/__init__.py
nowplaypadgen/dlplus.py
nowplaypadgen/py.typed
nowplaypadgen/renderer/__init__.py
nowplaypadgen/renderer/odr.py
nowplaypadgen/show.py
nowplaypadgen/timeperiod.py
nowplaypadgen/track.py
nowplaypadgen/util.py
nowplaypadgen-0.6.2.dist-info/METADATA
nowplaypadgen-0.6.2.dist-info/WHEEL
nowplaypadgen-0.6.2.dist-info/licenses/LICENSE
nowplaypadgen-0.6.2.dist-info/RECORD
