Metadata-Version: 2.4
Name: nowplaypadgen
Version: 0.6.2
Summary: DAB+ now playing PAD (DLS+ generator)
License: AGPL-3
License-File: LICENSE
Author: RaBe IT-Reaktion
Author-email: it@rabe.ch
Requires-Python: >=3.12,<4.0
Classifier: Development Status :: 3 - Alpha
Classifier: License :: OSI Approved :: GNU Affero General Public License v3
Classifier: License :: Other/Proprietary License
Classifier: Programming Language :: Python :: 3
Classifier: Programming Language :: Python :: 3.12
Classifier: Programming Language :: Python :: 3.13
Classifier: Programming Language :: Python :: 3.14
Requires-Dist: mutagen (>=1.47.0)
Requires-Dist: pytz (>=2024.2.0)
Project-URL: Repository, https://github.com/radiorabe/nowplaypadgen
